mingru_keras/__init__.py
mingru_keras/core.py
mingru_keras/py.typed
mingru_keras-0.1.3.dist-info/METADATA
mingru_keras-0.1.3.dist-info/WHEEL
mingru_keras-0.1.3.dist-info/licenses/LICENSE
mingru_keras-0.1.3.dist-info/RECORD
