Metadata-Version: 2.4
Name: mingru-keras
Version: 0.1.3
Summary: This package contains a Keras 3 implementation of the minGRU layer, a minimal and parallelizable version of the gated recurrent unit (GRU).
Author-email: Boris Reuderink <boris@cortext.nl>
License-File: LICENSE
Requires-Python: >=3.10
Requires-Dist: keras>=3.5.0
Provides-Extra: jax
Requires-Dist: jax>=0.4.34; extra == 'jax'
Provides-Extra: metal
Requires-Dist: tensorflow-macos>=2.16.2; extra == 'metal'
Requires-Dist: tensorflow-metal>=1.1.0; extra == 'metal'
Provides-Extra: test
Requires-Dist: pytest>=8.3.3; extra == 'test'
